{
  "y3_persistence": [
    {
      "split": "val",
      "n": 1194,
      "mae": 9971.524723618091,
      "rmse": 17399.17495929473,
      "mae_vs_predict_zero": 0.29703776870191695
    },
    {
      "split": "test",
      "n": 1990,
      "mae": 8796.12607035176,
      "rmse": 15363.964476995632,
      "mae_vs_predict_zero": 0.30038578472924166
    },
    {
      "split": "shock_holdout",
      "n": 2388,
      "mae": 8636.998295644891,
      "rmse": 14787.948803057909,
      "mae_vs_predict_zero": 0.2961037929325392
    }
  ],
  "y6_persistence": [
    {
      "split": "val",
      "n": 1194,
      "mae": 18151.50944723618,
      "rmse": 31519.980564161935,
      "mae_vs_predict_zero": 0.29352249742795333
    },
    {
      "split": "test",
      "n": 796,
      "mae": 15924.69981155779,
      "rmse": 26971.30372609803,
      "mae_vs_predict_zero": 0.2740158760346111
    },
    {
      "split": "shock_holdout",
      "n": 2786,
      "mae": 18496.544002153623,
      "rmse": 30722.488906563387,
      "mae_vs_predict_zero": 0.31121319065420827
    }
  ]
}